Kibana52ZhongwenWendang/README.md
Kibana52ZhongwenWendang/__init__.py
Kibana52ZhongwenWendang/__main__.py
Kibana52ZhongwenWendang/file.epub
Kibana52ZhongwenWendang/index.html
Kibana52ZhongwenWendang/css/__init__.py
Kibana52ZhongwenWendang/css/annotations.css
Kibana52ZhongwenWendang/css/main.css
Kibana52ZhongwenWendang/css/normalize.css
Kibana52ZhongwenWendang/css/popup.css
Kibana52ZhongwenWendang/font/__init__.py
Kibana52ZhongwenWendang/font/fontello.eot
Kibana52ZhongwenWendang/font/fontello.svg
Kibana52ZhongwenWendang/font/fontello.ttf
Kibana52ZhongwenWendang/font/fontello.woff
Kibana52ZhongwenWendang/img/__init__.py
Kibana52ZhongwenWendang/img/annotator-glyph-sprite.png
Kibana52ZhongwenWendang/img/annotator-icon-sprite.png
Kibana52ZhongwenWendang/img/apple-touch-icon.png
Kibana52ZhongwenWendang/img/cancelfullscreen.png
Kibana52ZhongwenWendang/img/close.png
Kibana52ZhongwenWendang/img/fullscreen.png
Kibana52ZhongwenWendang/img/loader.gif
Kibana52ZhongwenWendang/img/menu-icon.png
Kibana52ZhongwenWendang/img/save.png
Kibana52ZhongwenWendang/img/saved.png
Kibana52ZhongwenWendang/img/settings-s.png
Kibana52ZhongwenWendang/img/settings.png
Kibana52ZhongwenWendang/img/star.png
Kibana52ZhongwenWendang/js/__init__.py
Kibana52ZhongwenWendang/js/epub.js
Kibana52ZhongwenWendang/js/epub.min.js
Kibana52ZhongwenWendang/js/epub.min.map
Kibana52ZhongwenWendang/js/hooks.min.js
Kibana52ZhongwenWendang/js/hooks.min.map
Kibana52ZhongwenWendang/js/reader.js
Kibana52ZhongwenWendang/js/reader.js.map
Kibana52ZhongwenWendang/js/reader.min.js
Kibana52ZhongwenWendang/js/reader.min.map
Kibana52ZhongwenWendang/js/hooks/__init__.py
Kibana52ZhongwenWendang/js/hooks/extensions/__init__.py
Kibana52ZhongwenWendang/js/hooks/extensions/highlight.js
Kibana52ZhongwenWendang/js/libs/__init__.py
Kibana52ZhongwenWendang/js/libs/jquery.min.js
Kibana52ZhongwenWendang/js/libs/localforage.min.js
Kibana52ZhongwenWendang/js/libs/screenfull.js
Kibana52ZhongwenWendang/js/libs/screenfull.min.js
kibana_5_2_zhongwen_wendang-2024.3.2.0.dist-info/METADATA
kibana_5_2_zhongwen_wendang-2024.3.2.0.dist-info/WHEEL
kibana_5_2_zhongwen_wendang-2024.3.2.0.dist-info/entry_points.txt
kibana_5_2_zhongwen_wendang-2024.3.2.0.dist-info/top_level.txt
kibana_5_2_zhongwen_wendang-2024.3.2.0.dist-info/RECORD
